setup.py
mydumper/__init__.py
mydumper/mydumper.py
mydumper.egg-info/PKG-INFO
mydumper.egg-info/SOURCES.txt
mydumper.egg-info/dependency_links.txt
mydumper.egg-info/entry_points.txt
mydumper.egg-info/requires.txt
mydumper.egg-info/top_level.txt